bawa_rohan/__init__.py
bawa_rohan/topsis.py
bawa_rohan/topsis_topsis.py
bawa_rohan-0.1.dist-info/LICENSE.txt
bawa_rohan-0.1.dist-info/METADATA
bawa_rohan-0.1.dist-info/WHEEL
bawa_rohan-0.1.dist-info/top_level.txt
bawa_rohan-0.1.dist-info/RECORD
