Metadata-Version: 2.1
Name: bawa-rohan
Version: 0.1
Summary: This package allows you to run topsis on your dataset for Multiple Attribute Decision Making(MADM) on python
Home-page: https://github.com/rohanthapar/topsis_rohan
Author: Rohan Bawa
Author-email: rohanbawa8f@gmail.com
License: MIT
Keywords: TOPSIS,DATA ANALYSTICS
Platform: UNKNOWN
Classifier: Development Status :: 3 - Alpha
Classifier: Intended Audience :: Developers
Classifier: Topic :: Software Development :: Build Tools
Classifier: License :: OSI Approved :: MIT License
Classifier: Programming Language :: Python :: 3
Classifier: Programming Language :: Python :: 3.4
Classifier: Programming Language :: Python :: 3.5
Classifier: Programming Language :: Python :: 3.6
Requires-Dist: numpy
